mist/__init__.py
mist/analyze_data/__init__.py
mist/analyze_data/analyzer.py
mist/analyze_data/analyzer_constants.py
mist/analyze_data/analyzer_utils.py
mist/cli/__init__.py
mist/cli/analyze_entrypoint.py
mist/cli/args.py
mist/cli/conversion_entrypoint.py
mist/cli/evaluation_entrypoint.py
mist/cli/inference_entrypoint.py
mist/cli/postprocess_entrypoint.py
mist/cli/preprocess_entrypoint.py
mist/cli/run_all_entrypoint.py
mist/cli/train_entrypoint.py
mist/conversion_tools/__init__.py
mist/conversion_tools/conversion_format_registry.py
mist/conversion_tools/conversion_utils.py
mist/conversion_tools/csv.py
mist/conversion_tools/msd.py
mist/data_loading/__init__.py
mist/data_loading/dali_loader.py
mist/data_loading/data_loading_constants.py
mist/data_loading/data_loading_utils.py
mist/evaluation/__init__.py
mist/evaluation/evaluation_utils.py
mist/evaluation/evaluator.py
mist/inference/__init__.py
mist/inference/inference_constants.py
mist/inference/inference_runners.py
mist/inference/inference_utils.py
mist/inference/predictor.py
mist/inference/ensemblers/__init__.py
mist/inference/ensemblers/base.py
mist/inference/ensemblers/ensembler_registry.py
mist/inference/ensemblers/mean.py
mist/inference/inferers/__init__.py
mist/inference/inferers/base.py
mist/inference/inferers/inferer_registry.py
mist/inference/inferers/sliding_window.py
mist/inference/tta/__init__.py
mist/inference/tta/strategies.py
mist/inference/tta/transforms.py
mist/loss_functions/__init__.py
mist/loss_functions/alpha_schedulers.py
mist/loss_functions/base.py
mist/loss_functions/deep_supervision_wrapper.py
mist/loss_functions/loss_registry.py
mist/loss_functions/loss_utils.py
mist/loss_functions/losses/__init__.py
mist/loss_functions/losses/boundary.py
mist/loss_functions/losses/cl_dice.py
mist/loss_functions/losses/dice.py
mist/loss_functions/losses/dice_cross_entropy.py
mist/loss_functions/losses/generalized_surface.py
mist/loss_functions/losses/hausdorff_one_sided.py
mist/metrics/__init__.py
mist_medical-1.0.0b0.dist-info/licenses/LICENSE
mist_medical-1.0.0b0.dist-info/METADATA
mist_medical-1.0.0b0.dist-info/WHEEL
mist_medical-1.0.0b0.dist-info/entry_points.txt
mist_medical-1.0.0b0.dist-info/top_level.txt
mist_medical-1.0.0b0.dist-info/RECORD
