Metadata-Version: 2.4
Name: mist-medical
Version: 1.0.0b0
Summary: MIST is a simple and scalable end-to-end framework for medical imaging segmentation.
Author: MIST Imaging LLC, Rice University, The University of Texas MD Anderson Cancer Center
Author-email: Adrian Celaya <aecelaya@rice.edu>, David Fuentes <dtfuentes@mdanderson.org>, Beatrice Riviere <riviere@rice.edu>
License: 
Project-URL: homepage, https://github.com/mist-medical/MIST
Project-URL: repository, https://github.com/mist-medical/MIST
Project-URL: documentation, https://mist-medical.readthedocs.io/
Keywords: deep learning,image segmentation,semantic segmentation,medical image analysis,medical image segmentation,nnUNet,U-Net,vision transformers,Swin UNETR
Classifier: Development Status :: 4 - Beta
Classifier: Programming Language :: Python :: 3
Classifier: License :: OSI Approved :: Apache Software License
Classifier: Topic :: Scientific/Engineering :: Artificial Intelligence
Classifier: Topic :: Scientific/Engineering :: Medical Science Apps.
Requires-Python: >=3.10
License-File: LICENSE
Requires-Dist: torch
Requires-Dist: monai
Requires-Dist: antspyx
Requires-Dist: simpleitk
Requires-Dist: numpy
Requires-Dist: pandas
Requires-Dist: rich
Requires-Dist: scipy
Requires-Dist: scikit-learn
Requires-Dist: scikit-image
Requires-Dist: nvidia-dali-cuda120
Requires-Dist: tensorboard
Requires-Dist: einops
Requires-Dist: pytest
Dynamic: license-file
